{
  "warnings": [
    {
      "file": "/Users/home/Documents/Cluster2/Sources/Annotation.swift",
      "line": 11,
      "symbol": "Annotation",
      "symbol_kind": "source.lang.swift.decl.class",
      "warning": "undocumented"
    },
    {
      "file": "/Users/home/Documents/Cluster2/Sources/Annotation.swift",
      "line": 12,
      "symbol": "Annotation.init(coordinate:)",
      "symbol_kind": "source.lang.swift.decl.function.method.instance",
      "warning": "undocumented"
    },
    {
      "file": "/Users/home/Documents/Cluster2/Sources/Annotation.swift",
      "line": 18,
      "symbol": "ClusterAnnotation",
      "symbol_kind": "source.lang.swift.decl.class",
      "warning": "undocumented"
    },
    {
      "file": "/Users/home/Documents/Cluster2/Sources/Annotation.swift",
      "line": 19,
      "symbol": "ClusterAnnotation.annotations",
      "symbol_kind": "source.lang.swift.decl.var.instance",
      "warning": "undocumented"
    },
    {
      "file": "/Users/home/Documents/Cluster2/Sources/Annotation.swift",
      "line": 21,
      "symbol": "ClusterAnnotation.isEqual(_:)",
      "symbol_kind": "source.lang.swift.decl.function.method.instance",
      "warning": "undocumented"
    },
    {
      "file": "/Users/home/Documents/Cluster2/Sources/Annotation.swift",
      "line": 40,
      "symbol": "ClusterAnnotationView",
      "symbol_kind": "source.lang.swift.decl.class",
      "warning": "undocumented"
    },
    {
      "file": "/Users/home/Documents/Cluster2/Sources/Annotation.swift",
      "line": 42,
      "symbol": "ClusterAnnotationView.countLabel",
      "symbol_kind": "source.lang.swift.decl.var.instance",
      "warning": "undocumented"
    },
    {
      "file": "/Users/home/Documents/Cluster2/Sources/Annotation.swift",
      "line": 56,
      "symbol": "ClusterAnnotationView.annotation",
      "symbol_kind": "source.lang.swift.decl.var.instance",
      "warning": "undocumented"
    },
    {
      "file": "/Users/home/Documents/Cluster2/Sources/Annotation.swift",
      "line": 62,
      "symbol": "ClusterAnnotationView.configure()",
      "symbol_kind": "source.lang.swift.decl.function.method.instance",
      "warning": "undocumented"
    },
    {
      "file": "/Users/home/Documents/Cluster2/Sources/Cluster.swift",
      "line": null,
      "symbol": "ClusterManagerDelegate",
      "symbol_kind": "source.lang.swift.decl.extension",
      "warning": "undocumented"
    },
    {
      "file": "/Users/home/Documents/Cluster2/Sources/Cluster.swift",
      "line": 12,
      "symbol": "ClusterManagerDelegate",
      "symbol_kind": "source.lang.swift.decl.protocol",
      "warning": "undocumented"
    },
    {
      "file": "/Users/home/Documents/Cluster2/Sources/Cluster.swift",
      "line": 44,
      "symbol": "ClusterManager",
      "symbol_kind": "source.lang.swift.decl.class",
      "warning": "undocumented"
    },
    {
      "file": "/Users/home/Documents/Cluster2/Sources/Cluster.swift",
      "line": 142,
      "symbol": "ClusterManager.queue",
      "symbol_kind": "source.lang.swift.decl.var.instance",
      "warning": "undocumented"
    },
    {
      "file": "/Users/home/Documents/Cluster2/Sources/Cluster.swift",
      "line": 144,
      "symbol": "ClusterManager.delegate",
      "symbol_kind": "source.lang.swift.decl.var.instance",
      "warning": "undocumented"
    },
    {
      "file": "/Users/home/Documents/Cluster2/Sources/Cluster.swift",
      "line": 146,
      "symbol": "ClusterManager.init()",
      "symbol_kind": "source.lang.swift.decl.function.method.instance",
      "warning": "undocumented"
    },
    {
      "file": "/Users/home/Documents/Cluster2/Sources/Cluster.swift",
      "line": 240,
      "symbol": "ClusterManager.clusteredAnnotations(zoomScale:visibleMapRect:operation:)",
      "symbol_kind": "source.lang.swift.decl.function.method.instance",
      "warning": "undocumented"
    },
    {
      "file": "/Users/home/Documents/Cluster2/Sources/Cluster.swift",
      "line": 343,
      "symbol": "ClusterManager.display(mapView:toAdd:toRemove:)",
      "symbol_kind": "source.lang.swift.decl.function.method.instance",
      "warning": "undocumented"
    },
    {
      "file": "/Users/home/Documents/Cluster2/Sources/Extensions.swift",
      "line": 33,
      "symbol": "==(_:_:)",
      "symbol_kind": "source.lang.swift.decl.function.free",
      "warning": "undocumented"
    },
    {
      "file": "/Users/home/Documents/Cluster2/Sources/QuadTree.swift",
      "line": 149,
      "symbol": "QuadTree",
      "symbol_kind": "source.lang.swift.decl.class",
      "warning": "undocumented"
    },
    {
      "file": "/Users/home/Documents/Cluster2/Sources/QuadTree.swift",
      "line": 153,
      "symbol": "QuadTree.init(rect:)",
      "symbol_kind": "source.lang.swift.decl.function.method.instance",
      "warning": "undocumented"
    },
    {
      "file": "/Users/home/Documents/Cluster2/Sources/QuadTree.swift",
      "line": 158,
      "symbol": "QuadTree.add(_:)",
      "symbol_kind": "source.lang.swift.decl.function.method.instance",
      "warning": "undocumented"
    },
    {
      "file": "/Users/home/Documents/Cluster2/Sources/QuadTree.swift",
      "line": 163,
      "symbol": "QuadTree.remove(_:)",
      "symbol_kind": "source.lang.swift.decl.function.method.instance",
      "warning": "undocumented"
    },
    {
      "file": "/Users/home/Documents/Cluster2/Sources/QuadTree.swift",
      "line": 167,
      "symbol": "QuadTree.annotations(in:)",
      "symbol_kind": "source.lang.swift.decl.function.method.instance",
      "warning": "undocumented"
    }
  ],
  "source_directory": "/Users/home/Documents/Cluster2"
}